pyupnptools/__init__.py
pyupnptools/http_header.py
pyupnptools/http_request.py
pyupnptools/http_server.py
pyupnptools/ssdp.py
pyupnptools/upnp.py
pyupnptools/upnp_action_invoke.py
pyupnptools/upnp_control_point.py
pyupnptools/upnp_event_sub.py
pyupnptools/upnp_model.py
pyupnptools/upnp_server.py
pyupnptools/upnp_soap.py
pyupnptools/upnp_url.py
pyupnptools/upnp_xml.py
pyupnptools-1.0.0.dist-info/METADATA
pyupnptools-1.0.0.dist-info/RECORD
pyupnptools-1.0.0.dist-info/WHEEL
pyupnptools-1.0.0.dist-info/top_level.txt
