Metadata-Version: 2.1
Name: pyupnptools
Version: 1.0.0
Summary: python upnp tools
Home-page: https://github.com/bjtj/python-upnp-tools
Author: bjtj
Author-email: bjtj10@gmail.com
License: UNKNOWN
Platform: UNKNOWN
Classifier: Programming Language :: Python :: 3
Classifier: License :: OSI Approved :: MIT License
Classifier: Operating System :: OS Independent
